winzy_selected_file/__init__.py
winzy_selected_file-0.1.0.dist-info/licenses/LICENSE
winzy_selected_file-0.1.0.dist-info/METADATA
winzy_selected_file-0.1.0.dist-info/WHEEL
winzy_selected_file-0.1.0.dist-info/entry_points.txt
winzy_selected_file-0.1.0.dist-info/top_level.txt
winzy_selected_file-0.1.0.dist-info/RECORD
