Metadata-Version: 2.4
Name: winzy-selected-file
Version: 0.1.0
Summary: Get selected files as a text file on mac os
Author: Sukhbinder Singh
License: Apache-2.0
Project-URL: Homepage, https://github.com/sukhbinder/winzy-selected-file
Project-URL: Changelog, https://github.com/sukhbinder/winzy-selected-file/releases
Project-URL: Issues, https://github.com/sukhbinder/winzy-selected-file/issues
Project-URL: CI, https://github.com/sukhbinder/winzy-selected-file/actions
Classifier: License :: OSI Approved :: Apache Software License
License-File: LICENSE
Requires-Dist: winzy
Provides-Extra: test
Requires-Dist: pytest; extra == "test"
Dynamic: license-file
